developergpt/__init__.py
developergpt/__main__.py
developergpt/anthropic_adapter.py
developergpt/cli.py
developergpt/config.py
developergpt/few_shot_prompts.py
developergpt/gemini_adapter.py
developergpt/huggingface_adapter.py
developergpt/openai_adapter.py
developergpt/utils.py
developergpt-0.7.5.dist-info/LICENSE
developergpt-0.7.5.dist-info/METADATA
developergpt-0.7.5.dist-info/WHEEL
developergpt-0.7.5.dist-info/entry_points.txt
developergpt-0.7.5.dist-info/top_level.txt
developergpt-0.7.5.dist-info/RECORD
