Metadata-Version: 2.1
Name: developergpt
Version: 0.7.5
Summary: DeveloperGPT is a LLM-powered command line tool that enables natural language to terminal commands and in-terminal chat.
Home-page: https://github.com/luo-anthony/DeveloperGPT/
Author: luo-anthony
Requires-Python: >=3.9
License-File: LICENSE
Requires-Dist: openai >=1.1.0
Requires-Dist: google-generativeai >=0.4.1
Requires-Dist: pydantic <2.0.0
Requires-Dist: text-generation >=0.6.0
Requires-Dist: click
Requires-Dist: tiktoken
Requires-Dist: rich
Requires-Dist: inquirer
Requires-Dist: prompt-toolkit
Requires-Dist: pyperclip
Requires-Dist: requests
Requires-Dist: llama-cpp-python
Requires-Dist: huggingface-hub >=0.22.2
Requires-Dist: minijinja
Requires-Dist: anthropic >=0.23.0
Provides-Extra: test
Requires-Dist: pytest ; extra == 'test'
Requires-Dist: coverage ; extra == 'test'
Requires-Dist: flake8 ; extra == 'test'
Requires-Dist: black ; extra == 'test'
Requires-Dist: isort ; extra == 'test'
Requires-Dist: pytest-cov ; extra == 'test'
Requires-Dist: mypy ; extra == 'test'
Requires-Dist: gitchangelog ; extra == 'test'
Requires-Dist: mkdocs ; extra == 'test'
Requires-Dist: autopep8 ; extra == 'test'
Requires-Dist: types-requests ; extra == 'test'
